verilog_tp5/rtl/sf_fp16_mul.v
`timescale 1ns/1ps
// Binary16 academic multiplier. Subnormals are deliberately flushed to zero.
module sf_fp16_mul(input wire [15:0] a,input wire [15:0] b,output reg [15:0] result,output reg invalid,output reg overflow,output reg underflow);
reg sign;reg[4:0]ea,eb;reg[9:0]fa,fb;reg[10:0]ma,mb;reg[21:0]prod;integer exp_i;reg[9:0]frac_out;
 always @* begin sign=a[15]^b[15];ea=a[14:10];eb=b[14:10];fa=a[9:0];fb=b[9:0];ma=0;mb=0;prod=0;exp_i=0;frac_out=0;invalid=0;overflow=0;underflow=0;result=0;
if((ea==5'h1F&&fa!=0)||(eb==5'h1F&&fb!=0))begin result=16'h7E00;invalid=1;end
else if((ea==5'h1F&&eb==0&&fb==0)||(eb==5'h1F&&ea==0&&fa==0))begin result=16'h7E00;invalid=1;end
else if(ea==5'h1F||eb==5'h1F)result={sign,5'h1F,10'd0};
else if((ea==0&&fa==0)||(eb==0&&fb==0))result={sign,15'd0};
else if(ea==0||eb==0)begin result={sign,15'd0};underflow=1;end
else begin ma={1'b1,fa};mb={1'b1,fb};prod=ma*mb;exp_i=ea+eb-15;if(prod[21])begin exp_i=exp_i+1;frac_out=prod[20:11];end else frac_out=prod[19:10];if(exp_i>=31)begin result={sign,5'h1F,10'd0};overflow=1;end else if(exp_i<=0)begin result={sign,15'd0};underflow=1;end else result={sign,exp_i[4:0],frac_out};end end
endmodule

final_project/verilog_tp5/rtl/sf_fixed_q15_mac.v
`timescale 1ns/1ps
module sf_fixed_q15_mac(input wire signed [15:0] a_q15,input wire signed [15:0] b_q15,input wire signed [31:0] acc_q15,output reg signed [31:0] result_q15,output reg saturated);
reg signed [31:0] product;reg signed [63:0] scaled;reg signed [63:0] sum;
always @* begin product=a_q15*b_q15;scaled=$signed(product)>>>15;sum=scaled+$signed(acc_q15);saturated=1'b0;if(sum>64'sh000000007FFFFFFF)begin result_q15=32'sh7FFFFFFF;saturated=1'b1;end else if(sum < -64'sh0000000080000000)begin result_q15=32'sh80000000;saturated=1'b1;end else result_q15=sum[31:0];end
endmodule

verilog_tp5/tb/tb_arithmetic.v
`timescale 1ns/1ps
module tb_arithmetic;
reg signed[15:0]a,b;reg signed[31:0]acc;wire signed[31:0]qres;wire qsat;reg[15:0]fa,fb;wire[15:0]fres;wire finv,fovf,funf;integer checks,fails;
sf_fixed_q15_mac q(.a_q15(a),.b_q15(b),.acc_q15(acc),.result_q15(qres),.saturated(qsat));sf_fp16_mul f(.a(fa),.b(fb),.result(fres),.invalid(finv),.overflow(fovf),.underflow(funf));
task check_q;input signed[15:0]ta,tb;input signed[31:0]tacc,expected;input expected_sat;begin a=ta;b=tb;acc=tacc;#1;checks=checks+1;if(qres!==expected||qsat!==expected_sat)begin $display("FAIL Q15 a=%0d b=%0d acc=%0d got=%0d sat=%b exp=%0d/%b",ta,tb,tacc,qres,qsat,expected,expected_sat);fails=fails+1;end end endtask
task check_f;input[15:0]ta,tb,expected;input ei,eo,eu;begin fa=ta;fb=tb;#1;checks=checks+1;if(fres!==expected||finv!==ei||fovf!==eo||funf!==eu)begin $display("FAIL FP16 a=%h b=%h got=%h flags=%b%b%b exp=%h/%b%b%b",ta,tb,fres,finv,fovf,funf,expected,ei,eo,eu);fails=fails+1;end end endtask
initial begin $dumpfile("build/tb_arithmetic.vcd");$dumpvars(0,tb_arithmetic);checks=0;fails=0;a=0;b=0;acc=0;fa=0;fb=0;check_q(16'sh4000,16'sh4000,0,32'sd8192,0);check_q(-16'sh4000,16'sh4000,0,-32'sd8192,0);check_q(16'sh7fff,16'sh7fff,0,32'sd32766,0);check_q(16'sh4000,16'sh4000,32'sh7ffff000,32'sh7fffffff,1);check_f(16'h3E00,16'h4000,16'h4200,0,0,0);check_f(16'hC000,16'h3800,16'hBC00,0,0,0);check_f(16'h0000,16'h4500,16'h0000,0,0,0);check_f(16'h7BFF,16'h4000,16'h7C00,0,1,0);check_f(16'h7C00,16'h0000,16'h7E00,1,0,0);check_f(16'h0001,16'h3C00,16'h0000,0,0,1);if(fails==0)$display("TEST_RESULT: PASS arithmetic checks=%0d",checks);else $display("TEST_RESULT: FAIL arithmetic checks=%0d fails=%0d",checks,fails);$finish(fails!=0);end
endmodule

docs_tp5/evidence/simulation/waveforms/tb_arithmetic.vcd
$date
	Sun Sep 13 17:04:25 2026
$end
$version
	Icarus Verilog
$end
$timescale
	1ps
$end
$scope module tb_arithmetic $end
$var wire 1 ! qsat $end
$var wire 32 " qres [31:0] $end
$var wire 1 # funf $end
$var wire 16 $ fres [15:0] $end
$var wire 1 % fovf $end
$var wire 1 & finv $end
$var reg 16 ' a [15:0] $end
$var reg 32 ( acc [31:0] $end
$var reg 16 ) b [15:0] $end
$var reg 16 * fa [15:0] $end
$var reg 16 + fb [15:0] $end
$var integer 32 , checks [31:0] $end
$var integer 32 - fails [31:0] $end
$scope module f $end
$var wire 16 . a [15:0] $end
$var wire 16 / b [15:0] $end
$var reg 5 0 ea [4:0] $end
$var reg 5 1 eb [4:0] $end
$var reg 10 2 fa [9:0] $end
$var reg 10 3 fb [9:0] $end
$var reg 10 4 frac_out [9:0] $end
$var reg 1 5 invalid $end
$var reg 11 6 ma [10:0] $end
$var reg 11 7 mb [10:0] $end
$var reg 1 8 overflow $end
$var reg 22 9 prod [21:0] $end
$var reg 16 : result [15:0] $end
$var reg 1 ; sign $end
$var reg 1 < underflow $end
$var integer 32 = exp_i [31:0] $end
$upscope $end
$scope module q $end
$var wire 16 > a_q15 [15:0] $end
$var wire 32 ? acc_q15 [31:0] $end
$var wire 16 @ b_q15 [15:0] $end
$var reg 32 A product [31:0] $end
$var reg 32 B result_q15 [31:0] $end
$var reg 1 C saturated $end
$var reg 64 D scaled [63:0] $end
$var reg 64 E sum [63:0] $end
$upscope $end
$scope task check_f $end
$var reg 1 F ei $end
$var reg 1 G eo $end
$var reg 1 H eu $end
$var reg 16 I expected [15:0] $end
$var reg 16 J ta [15:0] $end
$var reg 16 K tb [15:0] $end
$upscope $end
$scope task check_q $end
$var reg 32 L expected [31:0] $end
$var reg 1 M expected_sat $end
$var reg 16 N ta [15:0] $end
$var reg 32 O tacc [31:0] $end
$var reg 16 P tb [15:0] $end
$upscope $end
$upscope $end
$enddefinitions $end
$comment Show the parameter values. $end
$dumpall
$end
#0
$dumpvars
b0 P
b0 O
b0 N
0M
b0 L
bx K
bx J
bx I
xH
xG
xF
b0 E
b0 D
0C
b0 B
b0 A
b0 @
b0 ?
b0 >
b0 =
0<
0;
b0 :
b0 9
08
b0 7
b0 6
05
b0 4
b0 3
b0 2
b0 1
b0 0
b0 /
b0 .
b0 -
b0 ,
b0 +
b0 *
b0 )
b0 (
b0 '
0&
0%
b0 $
0#
b0 "
0!
$end
#1000
b10000000000000 "
b10000000000000 B
b10000000000000 E
b10000000000000 D
b10000000000000000000000000000 A
b100000000000000 @
b100000000000000 )
b100000000000000 >
b100000000000000 '
b10000000000000 L
b100000000000000 P
b100000000000000 N
b1 ,
#2000
b11111111111111111110000000000000 "
b11111111111111111110000000000000 B
b1111111111111111111111111111111111111111111111111110000000000000 E
b1111111111111111111111111111111111111111111111111110000000000000 D
b11110000000000000000000000000000 A
b1100000000000000 >
b1100000000000000 '
b11111111111111111110000000000000 L
b1100000000000000 N
b10 ,
#3000
b111111111111110 "
b111111111111110 B
b111111111111110 E
b111111111111110 D
b111111111111110000000000000001 A
b111111111111111 @
b111111111111111 )
b111111111111111 >
b111111111111111 '
b111111111111110 L
b111111111111111 P
b111111111111111 N
b11 ,
#4000
b1000000000000000 "
b1000000000000000 B
b1000000000000000 E
b1000000000000000 D
b1000000000000000000000000000000 A
b1000000000000000 @
b1000000000000000 )
b1000000000000000 >
b1000000000000000 '
b1000000000000000 L
b1000000000000000 P
b1000000000000000 N
b100 ,
#5000
b1111111111111111111111111111110 "
b1111111111111111111111111111110 B
b1111111111111111111111111111110 E
b10000000000000 D
b10000000000000000000000000000 A
b1111111111111111101111111111110 ?
b1111111111111111101111111111110 (
b100000000000000 @
b100000000000000 )
b100000000000000 >
b100000000000000 '
b1111111111111111111111111111110 L
b1111111111111111101111111111110 O
b100000000000000 P
b100000000000000 N
b101 ,
#6000
b1111111111111111111111111111111 "
b1111111111111111111111111111111 B
b1111111111111111111111111111111 E
b1111111111111111101111111111111 ?
b1111111111111111101111111111111 (
b1111111111111111111111111111111 L
b1111111111111111101111111111111 O
b110 ,
#7000
1!
1C
b10000000000000000000000000000000 E
b1111111111111111110000000000000 ?
b1111111111111111110000000000000 (
1M
b1111111111111111110000000000000 O
b111 ,
#8000
b10000000000000000000000000000001 "
b10000000000000000000000000000001 B
0!
0C
b1111111111111111111111111111111110000000000000000000000000000001 E
b1111111111111111111111111111111111111111111111111110000000000000 D
b11110000000000000000000000000000 A
b10000000000000000010000000000001 ?
b10000000000000000010000000000001 (
b1100000000000000 >
b1100000000000000 '
0M
b10000000000000000000000000000001 L
b10000000000000000010000000000001 O
b1100000000000000 N
b1000 ,
#9000
b10000000000000000000000000000000 "
b10000000000000000000000000000000 B
b1111111111111111111111111111111110000000000000000000000000000000 E
b10000000000000000010000000000000 ?
b10000000000000000010000000000000 (
b10000000000000000000000000000000 L
b10000000000000000010000000000000 O
b1001 ,
#10000
1!
1C
b1111111111111111111111111111111101111111111111111111111111111111 E
b10000000000000000001111111111111 ?
b10000000000000000001111111111111 (
1M
b10000000000000000001111111111111 O
b1010 ,
#11000
b100001000000000 $
b100001000000000 :
b1000000000 4
b10000 =
b110000000000000000000 9
b10000000000 7
b11000000000 6
b1000000000 2
b10000 1
b1111 0
b100000000000000 /
b100000000000000 +
b11111000000000 .
b11111000000000 *
0H
0G
0F
b100001000000000 I
b100000000000000 K
b11111000000000 J
b1011 ,
#12000
b1011110000000000 $
b1011110000000000 :
b0 4
b1111 =
b100000000000000000000 9
b10000000000 7
b10000000000 6
b0 2
b1110 1
b10000 0
1;
b11100000000000 /
b11100000000000 +
b1100000000000000 .
b1100000000000000 *
b1011110000000000 I
b11100000000000 K
b1100000000000000 J
b1100 ,
#13000
b0 $
b0 :
b0 =
b0 9
b0 7
b0 6
b100000000 3
b10001 1
b0 0
0;
b100010100000000 /
b100010100000000 +
b0 .
b0 *
b0 I
b100010100000000 K
b0 J
b1101 ,
#14000
b1000000000000000 $
b1000000000000000 :
1;
b1000000000000000 .
b1000000000000000 *
b1000000000000000 I
b1000000000000000 J
b1110 ,
#15000
1%
18
b1111111111 4
b11111 =
b111111111110000000000 9
b10000000000 7
b11111111111 6
b111110000000000 $
b111110000000000 :
b0 3
b1111111111 2
b10000 1
b11110 0
0;
b100000000000000 /
b100000000000000 +
b111101111111111 .
b111101111111111 *
1G
b111110000000000 I
b100000000000000 K
b111101111111111 J
b1111 ,
#16000
b1111110000000000 $
b1111110000000000 :
1%
18
b1111111111 4
b11111 =
b111111111110000000000 9
b10000000000 7
b11111111111 6
1;
b1111101111111111 .
b1111101111111111 *
b1111110000000000 I
b1111101111111111 J
b10000 ,
#17000
1&
15
b111111000000000 $
b111111000000000 :
0%
08
b0 4
b0 =
b0 9
b0 7
b0 6
b0 2
b0 1
b11111 0
0;
b0 /
b0 +
b111110000000000 .
b111110000000000 *
0G
1F
b111111000000000 I
b0 K
b111110000000000 J
b10001 ,
#18000
b111111000000000 $
b111111000000000 :
1&
15
b1000000000 2
b1111 1
b11110000000000 /
b11110000000000 +
b111111000000000 .
b111111000000000 *
b11110000000000 K
b111111000000000 J
b10010 ,
#19000
b111110000000000 $
b111110000000000 :
0&
05
b0 2
b1011110000000000 /
b1011110000000000 +
b1111110000000000 .
b1111110000000000 *
0F
b111110000000000 I
b1011110000000000 K
b1111110000000000 J
b10011 ,
#20000
1#
1<
b0 $
b0 :
b1 2
b0 0
b11110000000000 /
b11110000000000 +
b1 .
b1 *
1H
b0 I
b11110000000000 K
b1 J
b10100 ,
#21000
b100000000000000000000 9
b10000000000 7
b10000000000 6
1#
1<
b0 2
b1110 1
b1 0
b11100000000000 /
b11100000000000 +
b10000000000 .
b10000000000 *
b11100000000000 K
b10000000000 J
b10101 ,
#22000
b1000000000000000 $
b1000000000000000 :
1#
1<
b100000000000000000000 9
b10000000000 7
b10000000000 6
1;
b1000010000000000 .
b1000010000000000 *
b1000000000000000 I
b1000010000000000 J
b10110 ,
#23000
b10111 ,
