verilog_tp5/rtl/uart_rx_byte.v
`timescale 1ns/1ps
// UART 8N1: two-flop asynchronous input synchronizer. CLKS_PER_BIT >= 8.
module uart_rx_byte #(parameter integer CLKS_PER_BIT=234)(
 input wire clk,input wire reset_n,input wire rx,
 output reg[7:0]data,output reg valid,output reg framing_error);
localparam S_IDLE=0,S_START=1,S_DATA=2,S_STOP=3;
reg[1:0]state;reg rx_meta,rx_sync;integer clk_count;reg[2:0]bit_index;reg[7:0]shift;
always@(posedge clk or negedge reset_n)begin
 if(!reset_n)begin rx_meta<=1'b1;rx_sync<=1'b1;end
 else begin rx_meta<=rx;rx_sync<=rx_meta;end
end
always@(posedge clk or negedge reset_n)begin
 if(!reset_n)begin state<=S_IDLE;clk_count<=0;bit_index<=0;shift<=0;data<=0;valid<=0;framing_error<=0;end
 else begin
  valid<=0;framing_error<=0;
  case(state)
   S_IDLE:if(!rx_sync)begin state<=S_START;clk_count<=0;end
   S_START:begin
    if(clk_count==((CLKS_PER_BIT-1)/2))begin
     if(!rx_sync)begin state<=S_DATA;clk_count<=0;bit_index<=0;end
     else state<=S_IDLE;
    end else clk_count<=clk_count+1;
   end
   S_DATA:begin
    if(clk_count==CLKS_PER_BIT-1)begin
     clk_count<=0;shift[bit_index]<=rx_sync;
     if(bit_index==7)state<=S_STOP;else bit_index<=bit_index+1'b1;
    end else clk_count<=clk_count+1;
   end
   S_STOP:begin
    if(clk_count==CLKS_PER_BIT-1)begin
     clk_count<=0;
     if(rx_sync)begin data<=shift;valid<=1'b1;end else framing_error<=1'b1;
     state<=S_IDLE;
    end else clk_count<=clk_count+1;
   end
   default:begin state<=S_IDLE;clk_count<=0;end
  endcase
 end
end
endmodule

verilog_tp5/rtl/sf_command_rx.v
`timescale 1ns/1ps
module sf_command_rx #(parameter integer UART_CLKS_PER_BIT=234)(input wire clk,input wire reset_n,input wire uart_rx,input wire command_ready,output reg command_valid,output reg [7:0] command_id,output reg [15:0] command_sequence,output reg [31:0] command_payload,output reg checksum_error,output wire framing_error);
wire [7:0] rx_byte;wire rx_valid;uart_rx_byte #(.CLKS_PER_BIT(UART_CLKS_PER_BIT)) rx0(.clk(clk),.reset_n(reset_n),.rx(uart_rx),.data(rx_byte),.valid(rx_valid),.framing_error(framing_error));
reg [3:0] index;reg [7:0] crc;reg [7:0] cmd_tmp;reg [15:0] seq_tmp;reg [31:0] payload_tmp;
function [7:0] crc8_next;input [7:0] current;input [7:0] value;integer i;reg [7:0] c;begin c=current^value;for(i=0;i<8;i=i+1)c=c[7]?((c<<1)^8'h07):(c<<1);crc8_next=c;end endfunction
always @(posedge clk or negedge reset_n) begin
 if(!reset_n) begin index<=0;crc<=0;command_valid<=0;command_id<=0;command_sequence<=0;command_payload<=0;checksum_error<=0;cmd_tmp<=0;seq_tmp<=0;payload_tmp<=0;end else begin
 checksum_error<=0;if(command_valid&&command_ready)command_valid<=0;
 if(rx_valid&&!command_valid)case(index)
 0:if(rx_byte==8'hA6)index<=1;else index<=0;
 1:begin if(rx_byte==8'h6A)begin index<=2;crc<=0;end else if(rx_byte==8'hA6)index<=1;else index<=0;end
 2:begin if(rx_byte==8'h05)begin crc<=crc8_next(0,rx_byte);index<=3;end else index<=0;end
 3:begin cmd_tmp<=rx_byte;crc<=crc8_next(crc,rx_byte);index<=4;end
 4:begin seq_tmp[15:8]<=rx_byte;crc<=crc8_next(crc,rx_byte);index<=5;end
 5:begin seq_tmp[7:0]<=rx_byte;crc<=crc8_next(crc,rx_byte);index<=6;end
 6:begin payload_tmp[31:24]<=rx_byte;crc<=crc8_next(crc,rx_byte);index<=7;end
 7:begin payload_tmp[23:16]<=rx_byte;crc<=crc8_next(crc,rx_byte);index<=8;end
 8:begin payload_tmp[15:8]<=rx_byte;crc<=crc8_next(crc,rx_byte);index<=9;end
 9:begin payload_tmp[7:0]<=rx_byte;crc<=crc8_next(crc,rx_byte);index<=10;end
 10:begin if(rx_byte==crc)begin command_id<=cmd_tmp;command_sequence<=seq_tmp;command_payload<=payload_tmp;command_valid<=1'b1;end else checksum_error<=1'b1;index<=0;end
 default:index<=0;endcase end end
endmodule

final_project/verilog_tp5/tb/tb_command_rx.v
`timescale 1ns/1ps
module tb_command_rx;
localparam CPB=16;
reg clk=0,reset_n=0,rx=1,ready=0;wire valid;wire[7:0]cmd;wire[15:0]seq;wire[31:0]payload;
wire crc_error,frame_error;integer fails=0,crc_count=0;always #5 clk=~clk;
always@(posedge clk)if(crc_error)crc_count=crc_count+1;
sf_command_rx #(.UART_CLKS_PER_BIT(CPB))dut(.clk(clk),.reset_n(reset_n),.uart_rx(rx),.command_ready(ready),.command_valid(valid),.command_id(cmd),.command_sequence(seq),.command_payload(payload),.checksum_error(crc_error),.framing_error(frame_error));
function[7:0]crc8_next;input[7:0]current,inputv;integer i;reg[7:0]c;
begin c=current^inputv;for(i=0;i<8;i=i+1)c=c[7]?((c<<1)^8'h07):(c<<1);crc8_next=c;end endfunction
task send_byte;input[7:0]v;integer i;
begin @(negedge clk);rx=0;repeat(CPB)@(negedge clk);for(i=0;i<8;i=i+1)begin rx=v[i];repeat(CPB)@(negedge clk);end rx=1;repeat(CPB)@(negedge clk);end endtask
task send_frame;input[7:0]c;input[15:0]s;input[31:0]p;input corrupt;reg[7:0]cc;
begin cc=0;cc=crc8_next(cc,8'h05);cc=crc8_next(cc,c);cc=crc8_next(cc,s[15:8]);cc=crc8_next(cc,s[7:0]);cc=crc8_next(cc,p[31:24]);cc=crc8_next(cc,p[23:16]);cc=crc8_next(cc,p[15:8]);cc=crc8_next(cc,p[7:0]);send_byte(8'hA6);send_byte(8'h6A);send_byte(8'h05);send_byte(c);send_byte(s[15:8]);send_byte(s[7:0]);send_byte(p[31:24]);send_byte(p[23:16]);send_byte(p[15:8]);send_byte(p[7:0]);send_byte(corrupt?(cc^8'h01):cc);end endtask
initial begin #1000000;$fatal(1,"FAIL command watchdog");end
initial begin
 $dumpfile("build/tb_command_rx.vcd");$dumpvars(0,tb_command_rx);
 repeat(4)@(negedge clk);reset_n=1;
 send_frame(8'h10,16'h1234,32'h40004000,0);repeat(8)@(negedge clk);
 if(!valid||cmd!==8'h10||seq!==16'h1234||payload!==32'h40004000)fails=fails+1;
 repeat(50)begin @(negedge clk);if(!valid||seq!==16'h1234)fails=fails+1;end
 ready=1;repeat(2)@(negedge clk);if(valid)fails=fails+1;ready=0;
 send_frame(8'h11,16'h1235,32'h3E004000,1);repeat(8)@(negedge clk);
 if(valid||crc_count!=1)begin $display("FAIL CRC rejection/count");fails=fails+1;end
 send_frame(8'h01,16'h1236,32'h00000000,0);repeat(8)@(negedge clk);
 if(!valid||seq!==16'h1236)begin $display("FAIL recovery after CRC");fails=fails+1;end
 if(fails!=0)$fatal(1,"TEST_RESULT: FAIL command_rx failures=%0d",fails);
 $display("TEST_RESULT: PASS command_rx hold+CRC+recovery");$finish;
end
endmodule

final_project/docs_tp5/evidence/simulation/waveforms/tb_command_rx.vcd
$date
	Sun Sep 13 17:04:26 2026
$end
$version
	Icarus Verilog
$end
$timescale
	1ps
$end
$scope module tb_command_rx $end
$var wire 1 ! valid $end
$var wire 16 " seq [15:0] $end
$var wire 32 # payload [31:0] $end
$var wire 1 $ frame_error $end
$var wire 1 % crc_error $end
$var wire 8 & cmd [7:0] $end
$var parameter 32 ' CPB $end
$var reg 1 ( clk $end
$var reg 1 ) ready $end
$var reg 1 * reset_n $end
$var reg 1 + rx $end
$var integer 32 , crc_count [31:0] $end
$var integer 32 - fails [31:0] $end
$scope function crc8_next $end
$var reg 8 . c [7:0] $end
$var reg 8 / current [7:0] $end
$var reg 8 0 inputv [7:0] $end
$var integer 32 1 i [31:0] $end
$upscope $end
$scope module dut $end
$var wire 1 2 clk $end
$var wire 1 3 command_ready $end
$var wire 1 4 reset_n $end
$var wire 1 5 uart_rx $end
$var wire 1 6 rx_valid $end
$var wire 8 7 rx_byte [7:0] $end
$var wire 1 8 framing_error $end
$var parameter 32 9 UART_CLKS_PER_BIT $end
$var reg 1 : checksum_error $end
$var reg 8 ; cmd_tmp [7:0] $end
$var reg 8 < command_id [7:0] $end
$var reg 32 = command_payload [31:0] $end
$var reg 16 > command_sequence [15:0] $end
$var reg 1 ? command_valid $end
$var reg 8 @ crc [7:0] $end
$var reg 4 A index [3:0] $end
$var reg 32 B payload_tmp [31:0] $end
$var reg 16 C seq_tmp [15:0] $end
$scope function crc8_next $end
$var reg 8 D c [7:0] $end
$var reg 8 E current [7:0] $end
$var reg 8 F value [7:0] $end
$var integer 32 G i [31:0] $end
$upscope $end
$scope module rx0 $end
$var wire 1 H clk $end
$var wire 1 I reset_n $end
$var wire 1 J rx $end
$var parameter 32 K CLKS_PER_BIT $end
$var parameter 32 L S_DATA $end
$var parameter 32 M S_IDLE $end
$var parameter 32 N S_START $end
$var parameter 32 O S_STOP $end
$var reg 3 P bit_index [2:0] $end
$var reg 8 Q data [7:0] $end
$var reg 1 R framing_error $end
$var reg 1 S rx_meta $end
$var reg 1 T rx_sync $end
$var reg 8 U shift [7:0] $end
$var reg 2 V state [1:0] $end
$var reg 1 W valid $end
$var integer 32 X clk_count [31:0] $end
$upscope $end
$upscope $end
$scope task send_byte $end
$var reg 8 Y v [7:0] $end
$var integer 32 Z i [31:0] $end
$upscope $end
$scope task send_frame $end
$var reg 8 [ c [7:0] $end
$var reg 8 \ cc [7:0] $end
$var reg 1 ] corrupt $end
$var reg 32 ^ p [31:0] $end
$var reg 16 _ s [15:0] $end
$upscope $end
$upscope $end
$enddefinitions $end
$comment Show the parameter values. $end
$dumpall
b11 O
b1 N
b0 M
b10 L
b10000 K
b10000 9
b10000 '
$end
#0
$dumpvars
bx _
bx ^
x]
bx \
bx [
bx Z
bx Y
bx X
xW
bx V
bx U
xT
xS
xR
bx Q
bx P
1J
0I
0H
bx G
bx F
bx E
bx D
bx C
bx B
bx A
bx @
x?
bx >
bx =
bx <
bx ;
x:
x8
bx 7
x6
15
04
03
02
bx 1
bx 0
bx /
bx .
b0 -
b0 ,
1+
0*
0)
0(
bx &
x%
x$
bx #
bx "
x!
$end
#5000
b0 B
b0 C
b0 ;
0%
0:
b0 #
b0 =
b0 "
b0 >
b0 &
b0 <
0!
0?
b0 @
b0 A
1T
1S
0$
08
0R
06
0W
b0 7
b0 Q
b0 U
b0 P
b0 X
b0 V
1H
12
1(
#10000
0H
02
0(
#15000
1H
12
1(
#20000
0H
02
0(
#25000
1H
12
1(
#30000
0H
02
0(
#35000
1H
12
1(
#40000
b10100110 Y
b1000 1
b1011001 .
b1110010 /
b0 0
b1011001 \
0]
b1000000000000000100000000000000 ^
b1001000110100 _
b10000 [
1I
14
1*
0H
02
0(
#45000
1H
12
1(
#50000
0J
05
0+
0H
02
0(
#55000
0S
1H
12
1(
#60000
0H
02
0(
#65000
0T
1H
12
1(
#70000
0H
02
0(
#75000
b1 V
1H
12
1(
#80000
0H
02
0(
#85000
b1 X
1H
12
1(
#90000
0H
02
0(
#95000
b10 X
1H
12
1(
#100000
0H
02
0(
#105000
b11 X
1H
12
1(
#110000
0H
02
0(
#115000
b100 X
1H
12
1(
#120000
0H
02
0(
#125000
b101 X
1H
12
1(
#130000
0H
02
0(
#135000
b110 X
1H
12
1(
#140000
0H
02
0(
#145000
b111 X
1H
12
1(
#150000
0H
02
0(
#155000
b0 X
b10 V
1H
12
1(
#160000
0H
02
0(
#165000
b1 X
1H
12
1(
#170000
0H
02
0(
#175000
b10 X
1H
12
1(
#180000
0H
02
0(
#185000
b11 X
1H
12
1(
#190000
0H
02
0(
#195000
b100 X
1H
12
1(
#200000
0H
02
0(
#205000
b101 X
1H
12
1(
#210000
b0 Z
0H
02
0(
#215000
b110 X
1H
12
1(
#220000
0H
02
0(
#225000
b111 X
1H
12
1(
#230000
0H
02
0(
#235000
b1000 X
1H
12
1(
#240000
0H
02
0(
#245000
b1001 X
1H
12
1(
#250000
0H
02
0(
#255000
b1010 X
1H
12
1(
#260000
0H
02
0(
#265000
b1011 X
1H
12
1(
#270000
0H
02
0(
#275000
b1100 X
1H
12
1(
#280000
0H
02
0(
#285000
b1101 X
1H
12
1(
#290000
0H
02
0(
#295000
b1110 X
1H
12
1(
#300000
0H
02
0(
#305000
b1111 X
1H
12
1(
#310000
0H
02
0(
#315000
b1 P
b0 X
1H
12
1(
#320000
0H
02
0(
#325000
b1 X
1H
12
1(
#330000
0H
02
0(
#335000
b10 X
1H
12
1(
#340000
0H
02
0(
#345000
b11 X
1H
12
1(
#350000
0H
02
0(
#355000
b100 X
1H
12
1(
#360000
0H
02
0(
#365000
b101 X
1H
12
1(
#370000
1J
15
1+
b1 Z
0H
02
0(
#375000
b110 X
1S
1H
12
1(
#380000
0H
02
0(
#385000
1T
b111 X
1H
12
1(
#390000
0H
02
0(
#395000
b1000 X
1H
12
1(
#400000
0H
02
0(
#405000
b1001 X
1H
12
1(
#410000
0H
02
0(
#415000
b1010 X
1H
12
1(
#420000
0H
02
0(
#425000
b1011 X
1H
12
1(
#430000
0H
02
0(
#435000
b1100 X
1H
12
1(
#440000
0H
02
0(
#445000
b1101 X
1H
12
1(
#450000
0H
02
0(
#455000
b1110 X
1H
12
1(
#460000
0H
02
0(
#465000
b1111 X
1H
12
1(
#470000
0H
02
0(
#475000
b10 P
b10 U
b0 X
1H
12
1(
#480000
0H
02
0(
#485000
b1 X
1H
12
1(
#490000
0H
02
0(
#495000
b10 X
1H
12
1(
#500000
0H
02
0(
#505000
b11 X
1H
12
1(
#510000
0H
02
0(
#515000
b100 X
1H
12
1(
#520000
0H
02
0(
#525000
b101 X
1H
12
1(
#530000
b10 Z
0H
02
0(
#535000
b110 X
1H
12
1(
#540000
0H
02
0(
#545000
b111 X
1H
12
1(
#550000
0H
02
0(
#555000
b1000 X
1H
12
1(
#560000
0H
02
0(
#565000
b1001 X
1H
12
1(
#570000
0H
02
0(
#575000
b1010 X
1H
12
1(
#580000
0H
02
0(
#585000
b1011 X
1H
12
1(
#590000
0H
02
0(
#595000
b1100 X
1H
12
1(
#600000
0H
02
0(
#605000
b1101 X
1H
12
1(
#610000
0H
02
0(
#615000
b1110 X
1H
12
1(
#620000
0H
02
0(
#625000
b1111 X
1H
12
1(
#630000
0H
02
0(
#635000
b11 P
b110 U
b0 X
1H
12
1(
#640000
0H
02
0(
#645000
b1 X
1H
12
1(
#650000
0H
02
0(
#655000
b10 X
1H
12
1(
#660000
0H
02
0(
#665000
b11 X
1H
12
1(
#670000
0H
02
0(
#675000
b100 X
1H
12
1(
#680000
0H
02
0(
#685000
b101 X
1H
12
1(
#690000
0J
05
0+
b11 Z
0H
02
0(
#695000
b110 X
0S
1H
12
1(
#700000
0H
02
0(
#705000
0T
b111 X
1H
12
1(
#710000
0H
02
0(
#715000
b1000 X
1H
12
1(
#720000
0H
02
0(
#725000
b1001 X
1H
12
1(
#730000
0H
02
0(
#735000
b1010 X
1H
12
1(
#740000
0H
02
0(
#745000
b1011 X
1H
12
1(
#750000
0H
02
0(
#755000
b1100 X
1H
12
1(
#760000
0H
02
0(
#765000
b1101 X
1H
12
1(
#770000
0H
02
0(
#775000
b1110 X
1H
12
1(
#780000
0H
02
0(
#785000
b1111 X
1H
12
1(
#790000
0H
02
0(
#795000
b100 P
b0 X
1H
12
1(
#800000
0H
02
0(
#805000
b1 X
1H
12
1(
#810000
0H
02
0(
#815000
b10 X
1H
12
1(
#820000
0H
02
0(
#825000
b11 X
1H
12
1(
#830000
0H
02
0(
#835000
b100 X
1H
12
1(
#840000
0H
02
0(
#845000
b101 X
1H
12
1(
#850000
b100 Z
0H
02
0(
#855000
b110 X
1H
12
1(
#860000
0H
02
0(
#865000
b111 X
1H
12
1(
#870000
0H
02
0(
#875000
b1000 X
1H
12
1(
#880000
0H
02
0(
#885000
b1001 X
1H
12
1(
#890000
0H
02
0(
#895000
b1010 X
1H
12
1(
#900000
0H
02
0(
#905000
b1011 X
1H
12
1(
#910000
0H
02
0(
#915000
b1100 X
1H
12
1(
#920000
0H
02
0(
#925000
b1101 X
1H
12
1(
#930000
0H
02
0(
#935000
b1110 X
1H
12
1(
#940000
0H
02
0(
#945000
b1111 X
1H
12
1(
#950000
0H
02
0(
#955000
b101 P
b0 X
1H
12
1(
#960000
0H
02
0(
#965000
b1 X
1H
12
1(
#970000
0H
02
0(
#975000
b10 X
1H
12
1(
#980000
0H
02
0(
#985000
b11 X
1H
12
1(
#990000
0H
02
0(
#995000
b100 X
1H
12
1(
#1000000
0H
02
0(
#1005000
b101 X
1H
12
1(
#1010000
1J
15
1+
b101 Z
0H
02
0(
#1015000
b110 X
1S
1H
12
1(
#1020000
0H
02
0(
#1025000
1T
b111 X
1H
12
1(
#1030000
0H
02
0(
#1035000
b1000 X
1H
12
1(
#1040000
0H
02
0(
#1045000
b1001 X
1H
12
1(
#1050000
0H
02
0(
#1055000
b1010 X
1H
12
1(
#1060000
0H
02
0(
#1065000
b1011 X
1H
12
1(
#1070000
0H
02
0(
#1075000
b1100 X
1H
12
1(
#1080000
0H
02
0(
#1085000
b1101 X
1H
12
1(
#1090000
0H
02
0(
#1095000
b1110 X
1H
12
1(
#1100000
0H
02
0(
#1105000
b1111 X
1H
12
1(
#1110000
0H
02
0(
#1115000
b110 P
b100110 U
b0 X
1H
12
1(
#1120000
0H
02
0(
#1125000
b1 X
1H
12
1(
#1130000
0H
02
0(
#1135000
b10 X
1H
12
1(
#1140000
0H
02
0(
#1145000
b11 X
1H
12
1(
#1150000
0H
02
0(
#1155000
b100 X
1H
12
1(
#1160000
0H
02
0(
#1165000
b101 X
1H
12
1(
#1170000
0J
05
0+
b110 Z
0H
02
0(
#1175000
b110 X
0S
1H
12
1(
#1180000
0H
02
0(
#1185000
0T
b111 X
1H
12
1(
#1190000
0H
02
0(
#1195000
b1000 X
1H
12
1(
#1200000
0H
02
0(
#1205000
b1001 X
1H
12
1(
#1210000
0H
02
0(
#1215000
b1010 X
1H
12
1(
#1220000
0H
02
0(
#1225000
b1011 X
1H
12
1(
#1230000
0H
02
0(
#1235000
b1100 X
1H
12
1(
#1240000
0H
02
0(
#1245000
b1101 X
1H
12
1(
#1250000
0H
02
0(
#1255000
b1110 X
1H
12
1(
#1260000
0H
02
0(
#1265000
b1111 X
1H
12
1(
#1270000
0H
02
0(
#1275000
b111 P
b0 X
1H
12
1(
#1280000
0H
02
0(
#1285000
b1 X
1H
12
1(
#1290000
0H
02
0(
#1295000
b10 X
1H
12
1(
#1300000
0H
02
0(
#1305000
b11 X
1H
12
1(
#1310000
0H
02
0(
#1315000
b100 X
1H
12
1(
#1320000
0H
02
0(
#1325000
b101 X
1H
12
1(
#1330000
1J
15
1+
b111 Z
0H
02
0(
#1335000
b110 X
1S
1H
12
1(
#1340000
0H
02
0(
#1345000
1T
b111 X
1H
12
1(
#1350000
0H
02
0(
#1355000
b1000 X
1H
12
1(
#1360000
0H
02
0(
#1365000
b1001 X
1H
12
1(
#1370000
0H
02
0(
#1375000
b1010 X
1H
12
1(
#1380000
0H
02
0(
#1385000
b1011 X
1H
12
1(
#1390000
0H
02
0(
#1395000
b1100 X
1H
12
1(
#1400000
0H
02
0(
#1405000
b1101 X
1H
12
1(
#1410000
0H
02
0(
#1415000
b1110 X
1H
12
1(
#1420000
0H
02
0(
#1425000
b1111 X
1H
12
1(
#1430000
0H
02
0(
#1435000
b11 V
b10100110 U
b0 X
1H
12
1(
#1440000
0H
02
0(
#1445000
b1 X
1H
12
1(
#1450000
0H
02
0(
#1455000
b10 X
1H
12
1(
#1460000
0H
02
0(
#1465000
b11 X
1H
12
1(
#1470000
0H
02
0(
#1475000
b100 X
1H
12
1(
#1480000
0H
02
0(
#1485000
b101 X
1H
12
1(
#1490000
b1000 Z
0H
02
0(
#1495000
b110 X
1H
12
1(
#1500000
0H
02
0(
#1505000
b111 X
1H
12
1(
#1510000
0H
02
0(
#1515000
b1000 X
1H
12
1(
#1520000
0H
02
0(
#1525000
b1001 X
1H
12
1(
#1530000
0H
02
0(
#1535000
b1010 X
1H
12
1(
#1540000
0H
02
0(
#1545000
b1011 X
1H
12
1(
#1550000
0H
02
0(
#1555000
b1100 X
1H
12
1(
#1560000
0H
02
0(
#1565000
b1101 X
1H
12
1(
#1570000
0H
02
0(
#1575000
b1110 X
1H
12
1(
#1580000
0H
02
0(
#1585000
b1111 X
1H
12
1(
#1590000
0H
02
0(
#1595000
b0 V
16
1W
b10100110 7
b10100110 Q
b0 X
1H
12
1(
#1600000
0H
02
0(
#1605000
b1 A
06
0W
1H
12
1(
#1610000
0H
02
0(
#1615000
1H
12
1(
#1620000
0H
02
0(
#1625000
1H
12
1(
#1630000
0H
02
0(
#1635000
1H
12
1(
#1640000
0H
02
0(
#1645000
1H
12
1(
#1650000
b1101010 Y
0H
02
0(
#1655000
1H
12
1(
#1660000
0J
05
0+
0H
02
0(
#1665000
0S
1H
12
1(
#1670000
0H
02
0(
#1675000
0T
1H
12
1(
#1680000
0H
02
0(
#1685000
b1 V
1H
12
1(
#1690000
0H
02
0(
#1695000
b1 X
1H
12
1(
#1700000
0H
02
0(
#1705000
b10 X
1H
12
1(
#1710000
0H
02
0(
#1715000
b11 X
1H
12
1(
#1720000
0H
02
0(
#1725000
b100 X
1H
12
1(
#1730000
0H
02
0(
#1735000
b101 X
1H
12
1(
#1740000
0H
02
0(
#1745000
b110 X
1H
12
1(
#1750000
0H
02
0(
#1755000
b111 X
1H
12
1(
#1760000
0H
02
0(
#1765000
b0 P
b0 X
b10 V
1H
12
1(
#1770000
0H
02
0(
#1775000
b1 X
1H
12
1(
#1780000
0H
02
0(
#1785000
b10 X
1H
12
1(
#1790000
0H
02
0(
#1795000
b11 X
1H
12
1(
#1800000
0H
02
0(
#1805000
b100 X
1H
12
1(
#1810000
0H
02
0(
#1815000
b101 X
1H
12
1(
#1820000
b0 Z
0H
02
0(
#1825000
b110 X
1H
12
1(
#1830000
0H
02
0(
#1835000
b111 X
1H
12
1(
#1840000
0H
02
0(
#1845000
b1000 X
1H
12
1(
#1850000
0H
02
0(
#1855000
b1001 X
1H
12
1(
#1860000
0H
02
0(
#1865000
b1010 X
1H
12
1(
#1870000
0H
02
0(
#1875000
b1011 X
1H
12
1(
#1880000
0H
02
0(
#1885000
b1100 X
1H
12
1(
#1890000
0H
02
0(
#1895000
b1101 X
1H
12
1(
#1900000
0H
02
0(
#1905000
b1110 X
1H
12
1(
#1910000
0H
02
0(
#1915000
b1111 X
1H
12
1(
#1920000
0H
02
0(
#1925000
b1 P
b0 X
1H
12
1(
#1930000
0H
02
0(
#1935000
b1 X
1H
12
1(
#1940000
0H
02
0(
#1945000
b10 X
1H
12
1(
#1950000
0H
02
0(
#1955000
b11 X
1H
12
1(
#1960000
0H
02
0(
#1965000
b100 X
1H
12
1(
#1970000
0H
02
0(
#1975000
b101 X
1H
12
1(
#1980000
1J
15
1+
b1 Z
0H
02
0(
#1985000
1S
b110 X
1H
12
1(
#1990000
0H
02
0(
#1995000
b111 X
1T
1H
12
1(
#2000000
0H
02
0(
#2005000
b1000 X
1H
12
1(
#2010000
0H
02
0(
#2015000
b1001 X
1H
12
1(
#2020000
0H
02
0(
#2025000
b1010 X
1H
12
1(
#2030000
0H
02
0(
#2035000
b1011 X
1H
12
1(
#2040000
0H
02
0(
#2045000
b1100 X
1H
12
1(
#2050000
0H
02
0(
#2055000
b1101 X
1H
12
1(
#2060000
0H
02
0(
#2065000
b1110 X
1H
12
1(
#2070000
0H
02
0(
#2075000
b1111 X
1H
12
1(
#2080000
0H
02
0(
#2085000
b10 P
b0 X
1H
12
1(
#2090000
0H
02
0(
#2095000
b1 X
1H
12
1(
#2100000
0H
02
0(
#2105000
b10 X
1H
12
1(
#2110000
0H
02
0(
#2115000
b11 X
1H
12
1(
#2120000
0H
02
0(
#2125000
b100 X
1H
12
1(
#2130000
0H
02
0(
#2135000
b101 X
1H
12
1(
#2140000
0J
05
0+
b10 Z
0H
02
0(
#2145000
0S
b110 X
1H
12
1(
#2150000
0H
02
0(
#2155000
b111 X
0T
1H
12
1(
#2160000
0H
02
0(
#2165000
b1000 X
1H
12
1(
#2170000
0H
02
0(
#2175000
b1001 X
1H
12
1(
#2180000
0H
02
0(
#2185000
b1010 X
1H
12
1(
#2190000
0H
02
0(
#2195000
b1011 X
1H
12
1(
#2200000
0H
02
0(
#2205000
b1100 X
1H
12
1(
#2210000
0H
02
0(
#2215000
b1101 X
1H
12
1(
#2220000
0H
02
0(
#2225000
b1110 X
1H
12
1(
#2230000
0H
02
0(
#2235000
b1111 X
1H
12
1(
#2240000
0H
02
0(
#2245000
b11 P
b10100010 U
b0 X
1H
12
1(
#2250000
0H
02
0(
#2255000
b1 X
1H
12
1(
#2260000
0H
02
0(
#2265000
b10 X
1H
12
1(
#2270000
0H
02
0(
#2275000
b11 X
1H
12
1(
#2280000
0H
02
0(
#2285000
b100 X
1H
12
1(
#2290000
0H
02
0(
#2295000
b101 X
1H
12
1(
#2300000
1J
15
1+
b11 Z
0H
02
0(
#2305000
1S
b110 X
1H
12
1(
#2310000
0H
02
0(
#2315000
b111 X
1T
1H
12
1(
#2320000
0H
02
0(
#2325000
b1000 X
1H
12
1(
#2330000
0H
02
0(
#2335000
b1001 X
1H
12
1(
#2340000
0H
02
0(
#2345000
b1010 X
1H
12
1(
#2350000
0H
02
0(
#2355000
b1011 X
1H
12
1(
#2360000
0H
02
0(
#2365000
b1100 X
1H
12
1(
#2370000
0H
02
0(
#2375000
b1101 X
1H
12
1(
#2380000
0H
02
0(
#2385000
b1110 X
1H
12
1(
#2390000
0H
02
0(
#2395000
b1111 X
1H
12
1(
#2400000
0H
02
0(
#2405000
b100 P
b10101010 U
b0 X
1H
12
1(
#2410000
0H
02
0(
#2415000
b1 X
1H
12
1(
#2420000
0H
02
0(
#2425000
b10 X
1H
12
1(
#2430000
0H
02
0(
#2435000
b11 X
1H
12
1(
#2440000
0H
02
0(
#2445000
b100 X
1H
12
1(
#2450000
0H
02
0(
#2455000
b101 X
1H
12
1(
#2460000
0J
05
0+
b100 Z
0H
02
0(
#2465000
0S
b110 X
1H
12
1(
#2470000
0H
02
0(
#2475000
b111 X
0T
1H
12
1(
#2480000
0H
02
0(
#2485000
b1000 X
1H
12
1(
#2490000
0H
02
0(
#2495000
b1001 X
1H
12
1(
#2500000
0H
02
0(
#2505000
b1010 X
1H
12
1(
#2510000
0H
02
0(
#2515000
b1011 X
1H
12
1(
#2520000
0H
02
0(
#2525000
b1100 X
1H
12
1(
#2530000
0H
02
0(
#2535000
b1101 X
1H
12
1(
#2540000
0H
02
0(
#2545000
b1110 X
1H
12
1(
#2550000
0H
02
0(
#2555000
b1111 X
1H
12
1(
#2560000
0H
02
0(
#2565000
b101 P
b0 X
1H
12
1(
#2570000
0H
02
0(
#2575000
b1 X
1H
12
1(
#2580000
0H
02
0(
#2585000
b10 X
1H
12
1(
#2590000
0H
02
0(
#2595000
b11 X
1H
12
1(
#2600000
0H
02
0(
#2605000
b100 X
1H
12
1(
#2610000
0H
02
0(
#2615000
b101 X
1H
12
1(
#2620000
1J
15
1+
b101 Z
0H
02
0(
#2625000
1S
b110 X
1H
12
1(
#2630000
0H
02
0(
#2635000
b111 X
1T
1H
12
1(
#2640000
0H
02
0(
#2645000
b1000 X
1H
12
1(
#2650000
0H
02
0(
#2655000
b1001 X
1H
12
1(
#2660000
0H
02
0(
#2665000
b1010 X
1H
12
1(
#2670000
0H
02
0(
#2675000
b1011 X
1H
12
1(
#2680000
0H
02
0(
#2685000
b1100 X
1H
12
1(
#2690000
0H
02
0(
#2695000
b1101 X
1H
12
1(
#2700000
0H
02
0(
#2705000
b1110 X
1H
12
1(
#2710000
0H
02
0(
#2715000
b1111 X
1H
12
1(
#2720000
0H
02
0(
#2725000
b110 P
b0 X
1H
12
1(
#2730000
0H
02
0(
#2735000
b1 X
1H
12
1(
#2740000
0H
02
0(
#2745000
b10 X
1H
12
1(
#2750000
0H
02
0(
#2755000
b11 X
1H
12
1(
#2760000
0H
02
0(
#2765000
b100 X
1H
12
1(
#2770000
0H
02
0(
#2775000
b101 X
1H
12
1(
#2780000
b110 Z
0H
02
0(
#2785000
b110 X
1H
12
1(
#2790000
0H
02
0(
#2795000
b111 X
1H
12
1(
#2800000
0H
02
0(
#2805000
b1000 X
1H
12
1(
#2810000
0H
02
0(
#2815000
b1001 X
1H
12
1(
#2820000
0H
02
0(
#2825000
b1010 X
1H
12
1(
#2830000
0H
02
0(
#2835000
b1011 X
1H
12
1(
#2840000
0H
02
0(
#2845000
b1100 X
1H
12
1(
#2850000
0H
02
0(
#2855000
b1101 X
1H
12
1(
#2860000
0H
02
0(
#2865000
b1110 X
1H
12
1(
#2870000
0H
02
0(
#2875000
b1111 X
1H
12
1(
#2880000
0H
02
0(
#2885000
b111 P
b11101010 U
b0 X
1H
12
1(
#2890000
0H
02
0(
#2895000
b1 X
1H
12
1(
#2900000
0H
02
0(
#2905000
b10 X
1H
12
1(
#2910000
0H
02
0(
#2915000
b11 X
1H
12
1(
#2920000
0H
02
0(
#2925000
b100 X
1H
12
1(
#2930000
0H
02
0(
#2935000
b101 X
1H
12
1(
#2940000
0J
05
0+
b111 Z
0H
02
0(
#2945000
0S
b110 X
1H
12
1(
#2950000
0H
02
0(
#2955000
b111 X
0T
1H
12
1(
#2960000
0H
02
0(
#2965000
b1000 X
1H
12
1(
#2970000
0H
02
0(
#2975000
b1001 X
1H
12
1(
#2980000
0H
02
0(
#2985000
b1010 X
1H
12
1(
#2990000
0H
02
0(
#2995000
b1011 X
1H
12
1(
#3000000
0H
02
0(
#3005000
b1100 X
1H
12
1(
#3010000
0H
02
0(
#3015000
b1101 X
1H
12
1(
#3020000
0H
02
0(
#3025000
b1110 X
1H
12
1(
