verilog_tp4/rtl/safe_field_audio_energy_dsp.v
`timescale 1ns/1ps

// One physically relevant 16x16 signed multiplier. The 24-bit I2S sample is
// reduced to its most significant 16 bits before squaring, preserving sign.
// GowinSynthesis is explicitly directed to map the multiplier to one DSP.
module safe_field_audio_energy_dsp (
    input wire clk,
    input wire reset_n,
    input wire input_valid,
    input wire input_is_command,
    input wire signed [23:0] sample_signed,
    output reg result_valid,
    output reg result_is_command,
    output reg [31:0] sample_power
) /* synthesis syn_dspstyle = "dsp" */;
reg signed [15:0] sample_q;
reg valid_q;
reg command_q;

always @(posedge clk or negedge reset_n) begin
    if (!reset_n) begin
        sample_q <= 16'sd0;
        valid_q <= 1'b0;
        command_q <= 1'b0;
        result_valid <= 1'b0;
        result_is_command <= 1'b0;
        sample_power <= 32'd0;
    end else begin
        sample_q <= sample_signed[23:8];
        valid_q <= input_valid;
        command_q <= input_is_command;
        result_valid <= valid_q;
        result_is_command <= command_q;
        if (valid_q)
            sample_power <= $signed(sample_q) * $signed(sample_q);
    end
end
endmodule

verilog_tp4/tb/tb_safe_field_audio_energy_dsp.v
`timescale 1ns/1ps
module tb_safe_field_audio_energy_dsp;
reg clk=0, reset_n=0, input_valid=0, input_is_command=0;
reg signed [23:0] sample_signed=0;
wire result_valid, result_is_command;
wire [31:0] sample_power;
integer checks=0, errors=0;
always #5 clk=~clk;

safe_field_audio_energy_dsp dut(.*);

task check;
input [255:0] label; input [31:0] expected; input [31:0] actual;
begin checks=checks+1; if(expected!==actual) begin errors=errors+1; $display("FAIL %0s expected=%0d actual=%0d",label,expected,actual); end
else $display("PASS %0s expected=%0d actual=%0d",label,expected,actual); end
endtask

task apply;
input signed [15:0] value; input [31:0] expected; input [255:0] label;
begin
 @(negedge clk); sample_signed={value,8'b0}; input_valid=1; input_is_command=1;
 @(negedge clk); input_valid=0;
 wait(result_valid); #1; check(label,expected,sample_power); check("command tag",1,result_is_command);
end
endtask

initial begin
 $dumpfile("safe_field_audio_energy_dsp.vcd"); $dumpvars(0,tb_safe_field_audio_energy_dsp);
 repeat(3) @(negedge clk); reset_n=1;
 apply(16'sd0,32'd0,"zero squared");
 apply(16'sd123,32'd15129,"positive squared");
 apply(-16'sd123,32'd15129,"negative squared");
 apply(16'sd32767,32'd1073676289,"positive limit");
 apply(-16'sd32768,32'd1073741824,"negative limit without overflow");
 if(errors==0) $display("TEST_RESULT: PASS"); else $display("TEST_RESULT: FAIL errors=%0d",errors);
 $display("checks=%0d errors=%0d",checks,errors); $finish;
end
endmodule

evidence/official_tp4/waveforms/safe_field_audio_energy_dsp.vcd
$date
	Fri Sep  4 18:09:10 2026
$end
$version
	Icarus Verilog
$end
$timescale
	1ps
$end
$scope module tb_safe_field_audio_energy_dsp $end
$var wire 32 ! sample_power [31:0] $end
$var wire 1 " result_valid $end
$var wire 1 # result_is_command $end
$var reg 1 $ clk $end
$var reg 1 % input_is_command $end
$var reg 1 & input_valid $end
$var reg 1 ' reset_n $end
$var reg 24 ( sample_signed [23:0] $end
$var integer 32 ) checks [31:0] $end
$var integer 32 * errors [31:0] $end
$scope module dut $end
$var wire 1 + clk $end
$var wire 1 , input_is_command $end
$var wire 1 - input_valid $end
$var wire 1 . reset_n $end
$var wire 24 / sample_signed [23:0] $end
$var reg 1 0 command_q $end
$var reg 1 1 result_is_command $end
$var reg 1 2 result_valid $end
$var reg 32 3 sample_power [31:0] $end
$var reg 16 4 sample_q [15:0] $end
$var reg 1 5 valid_q $end
$upscope $end
$scope task apply $end
$var reg 32 6 expected [31:0] $end
$var reg 256 7 label [255:0] $end
$var reg 16 8 value [15:0] $end
$upscope $end
$scope task check $end
$var reg 32 9 actual [31:0] $end
$var reg 32 : expected [31:0] $end
$var reg 256 ; label [255:0] $end
$upscope $end
$upscope $end
$enddefinitions $end
$comment Show the parameter values. $end
$dumpall
$end
#0
$dumpvars
bx ;
bx :
bx 9
bx 8
bx 7
bx 6
x5
bx 4
bx 3
x2
x1
x0
b0 /
0.
0-
0,
0+
b0 *
b0 )
b0 (
0'
0&
0%
0$
x#
x"
bx !
$end
#5000
b0 !
b0 3
0#
01
0"
02
00
05
b0 4
1+
1$
#10000
0+
0$
#15000
1+
1$
#20000
0+
0$
#25000
1+
1$
#30000
b11110100110010101110010011011110010000001110011011100010111010101100001011100100110010101100100 7
b0 6
b0 8
1.
1'
0+
0$
#35000
1+
1$
#40000
1,
1%
1-
1&
0+
0$
#45000
10
15
1+
1$
#50000
0-
0&
0+
0$
#55000
1#
11
1"
12
05
1+
1$
#56000
b1110000011011110111001101101001011101000110100101110110011001010010000001110011011100010111010101100001011100100110010101100100 7
b11101100011001 6
b1111011 8
b10 )
b1 9
b1 :
b110001101101111011011010110110101100001011011100110010000100000011101000110000101100111 ;
#60000
1-
1&
b111101100000000 /
b111101100000000 (
0+
0$
#65000
0"
02
15
b1111011 4
1+
1$
#70000
0-
0&
0+
0$
#75000
b11101100011001 !
b11101100011001 3
1"
12
05
1+
1$
#76000
b1101110011001010110011101100001011101000110100101110110011001010010000001110011011100010111010101100001011100100110010101100100 7
b1111111110000101 8
b100 )
b1 9
b1 :
b110001101101111011011010110110101100001011011100110010000100000011101000110000101100111 ;
#80000
1-
1&
b111111111000010100000000 /
b111111111000010100000000 (
0+
0$
#85000
0"
02
15
b1111111110000101 4
1+
1$
#90000
0-
0&
0+
0$
#95000
1"
12
05
1+
1$
#96000
b111000001101111011100110110100101110100011010010111011001100101001000000110110001101001011011010110100101110100 7
b111111111111110000000000000001 6
b111111111111111 8
b110 )
b1 9
b1 :
b110001101101111011011010110110101100001011011100110010000100000011101000110000101100111 ;
#100000
1-
1&
b11111111111111100000000 /
b11111111111111100000000 (
0+
0$
#105000
0"
02
15
b111111111111111 4
1+
1$
#110000
0-
0&
0+
0$
#115000
b111111111111110000000000000001 !
b111111111111110000000000000001 3
1"
12
05
1+
1$
#116000
b1101110011001010110011101100001011101000110100101110110011001010010000001101100011010010110110101101001011101000010000001110111011010010111010001101000011011110111010101110100001000000110111101110110011001010111001001100110011011000110111101110111 7
b1000000000000000000000000000000 6
b1000000000000000 8
b1000 )
b1 9
b1 :
b110001101101111011011010110110101100001011011100110010000100000011101000110000101100111 ;
#120000
1-
1&
b100000000000000000000000 /
b100000000000000000000000 (
0+
0$
#125000
0"
02
15
b1000000000000000 4
1+
1$
#130000
0-
0&
0+
0$
#135000
b1000000000000000000000000000000 !
b1000000000000000000000000000000 3
1"
12
05
1+
1$
#136000
b1010 )
b1 9
b1 :
b110001101101111011011010110110101100001011011100110010000100000011101000110000101100111 ;
