verilog_tp4/rtl/safe_field_energy_bram.v
`timescale 1ns/1ps

// Functional 256 x 32-bit audio-power buffer plus a block average. Memory is
// read synchronously and is not reset, matching dedicated BSRAM behavior.
module safe_field_energy_bram (
    input wire clk,
    input wire reset_n,
    input wire power_valid,
    input wire [31:0] power_value,
    input wire [7:0] read_address,
    output reg [31:0] read_data,
    output reg [31:0] window_average,
    output reg window_valid,
    output reg [7:0] write_address
) /* synthesis syn_ramstyle = "block_ram" */;
reg [31:0] memory [0:255] /* synthesis syn_ramstyle = "block_ram" */;
reg [39:0] window_sum;

always @(posedge clk) begin
    read_data <= memory[read_address];
    if (power_valid)
        memory[write_address] <= power_value;
end

always @(posedge clk or negedge reset_n) begin
    if (!reset_n) begin
        write_address <= 8'd0;
        window_sum <= 40'd0;
        window_average <= 32'd0;
        window_valid <= 1'b0;
    end else begin
        window_valid <= 1'b0;
        if (power_valid) begin
            if (write_address == 8'hFF) begin
                window_average <= (window_sum + power_value) >> 8;
                window_sum <= 40'd0;
                write_address <= 8'd0;
                window_valid <= 1'b1;
            end else begin
                window_sum <= window_sum + power_value;
                write_address <= write_address + 1'b1;
            end
        end
    end
end
endmodule

verilog_tp4/tb/tb_safe_field_energy_bram.v
`timescale 1ns/1ps
module tb_safe_field_energy_bram;
reg clk=0,reset_n=0,power_valid=0;
reg [31:0] power_value=0;
reg [7:0] read_address=0;
wire [31:0] read_data,window_average;
wire window_valid;
wire [7:0] write_address;
integer i,checks=0,errors=0;
always #5 clk=~clk;
safe_field_energy_bram dut(.*);
task check; input [255:0] label; input [31:0] expected,actual;
begin checks=checks+1; if(expected!==actual) begin errors=errors+1;$display("FAIL %0s expected=%0d actual=%0d",label,expected,actual);end
else $display("PASS %0s expected=%0d actual=%0d",label,expected,actual);end endtask
initial begin
 $dumpfile("safe_field_energy_bram.vcd");$dumpvars(0,tb_safe_field_energy_bram);
 repeat(3)@(negedge clk);reset_n=1;
 for(i=0;i<256;i=i+1) begin @(negedge clk);power_valid=1;power_value=i;end
 @(negedge clk);power_valid=0; wait(window_valid);#1;
 check("average floor of 0..255",32'd127,window_average);
 read_address=8'd0; repeat(2)@(posedge clk);#1;check("BRAM address zero",32'd0,read_data);
 read_address=8'd123; repeat(2)@(posedge clk);#1;check("BRAM middle",32'd123,read_data);
 read_address=8'd255; repeat(2)@(posedge clk);#1;check("BRAM upper limit",32'd255,read_data);
 check("write pointer wrapped",32'd0,{24'd0,write_address});
 if(errors==0)$display("TEST_RESULT: PASS");else $display("TEST_RESULT: FAIL errors=%0d",errors);
 $display("checks=%0d errors=%0d",checks,errors);$finish;
end
endmodule

evidence/official_tp4/waveforms/safe_field_energy_bram.vcd
$date
	Fri Sep  4 18:09:10 2026
$end
$version
	Icarus Verilog
$end
$timescale
	1ps
$end
$scope module tb_safe_field_energy_bram $end
$var wire 8 ! write_address [7:0] $end
$var wire 1 " window_valid $end
$var wire 32 # window_average [31:0] $end
$var wire 32 $ read_data [31:0] $end
$var reg 1 % clk $end
$var reg 1 & power_valid $end
$var reg 32 ' power_value [31:0] $end
$var reg 8 ( read_address [7:0] $end
$var reg 1 ) reset_n $end
$var integer 32 * checks [31:0] $end
$var integer 32 + errors [31:0] $end
$var integer 32 , i [31:0] $end
$scope module dut $end
$var wire 1 - clk $end
$var wire 1 . power_valid $end
$var wire 32 / power_value [31:0] $end
$var wire 8 0 read_address [7:0] $end
$var wire 1 1 reset_n $end
$var reg 32 2 read_data [31:0] $end
$var reg 32 3 window_average [31:0] $end
$var reg 40 4 window_sum [39:0] $end
$var reg 1 5 window_valid $end
$var reg 8 6 write_address [7:0] $end
$upscope $end
$scope task check $end
$var reg 32 7 actual [31:0] $end
$var reg 32 8 expected [31:0] $end
$var reg 256 9 label [255:0] $end
$upscope $end
$upscope $end
$enddefinitions $end
$comment Show the parameter values. $end
$dumpall
$end
#0
$dumpvars
bx 9
bx 8
bx 7
bx 6
x5
bx 4
bx 3
bx 2
01
b0 0
b0 /
0.
0-
bx ,
b0 +
b0 *
0)
b0 (
b0 '
0&
0%
bx $
bx #
x"
bx !
$end
#5000
0"
05
b0 #
b0 3
b0 4
b0 !
b0 6
1-
1%
#10000
0-
0%
#15000
1-
1%
#20000
0-
0%
#25000
1-
1%
#30000
b0 ,
11
1)
0-
0%
#35000
1-
1%
#40000
b1 ,
1.
1&
0-
0%
#45000
b1 !
b1 6
1-
1%
#50000
b10 ,
b1 /
b1 '
0-
0%
#55000
b10 !
b10 6
b1 4
b0 $
b0 2
1-
1%
#60000
b11 ,
b10 /
b10 '
0-
0%
#65000
b11 !
b11 6
b11 4
1-
1%
#70000
b100 ,
b11 /
b11 '
0-
0%
#75000
b100 !
b100 6
b110 4
1-
1%
#80000
b101 ,
b100 /
b100 '
0-
0%
#85000
b101 !
b101 6
b1010 4
1-
1%
#90000
b110 ,
b101 /
b101 '
0-
0%
#95000
b110 !
b110 6
b1111 4
1-
1%
#100000
b111 ,
b110 /
b110 '
0-
0%
#105000
b111 !
b111 6
b10101 4
1-
1%
#110000
b1000 ,
b111 /
b111 '
0-
0%
#115000
b1000 !
b1000 6
b11100 4
1-
1%
#120000
b1001 ,
b1000 /
b1000 '
0-
0%
#125000
b1001 !
b1001 6
b100100 4
1-
1%
#130000
b1010 ,
b1001 /
b1001 '
0-
0%
#135000
b1010 !
b1010 6
b101101 4
1-
1%
#140000
b1011 ,
b1010 /
b1010 '
0-
0%
#145000
b1011 !
b1011 6
b110111 4
1-
1%
#150000
b1100 ,
b1011 /
b1011 '
0-
0%
#155000
b1100 !
b1100 6
b1000010 4
1-
1%
#160000
b1101 ,
b1100 /
b1100 '
0-
0%
#165000
b1101 !
b1101 6
b1001110 4
1-
1%
#170000
b1110 ,
b1101 /
b1101 '
0-
0%
#175000
b1110 !
b1110 6
b1011011 4
1-
1%
#180000
b1111 ,
b1110 /
b1110 '
0-
0%
#185000
b1111 !
b1111 6
b1101001 4
1-
1%
#190000
b10000 ,
b1111 /
b1111 '
0-
0%
#195000
b10000 !
b10000 6
b1111000 4
1-
1%
#200000
b10001 ,
b10000 /
b10000 '
0-
0%
#205000
b10001 !
b10001 6
b10001000 4
1-
1%
#210000
b10010 ,
b10001 /
b10001 '
0-
0%
#215000
b10010 !
b10010 6
b10011001 4
1-
1%
#220000
b10011 ,
b10010 /
b10010 '
0-
0%
#225000
b10011 !
b10011 6
b10101011 4
1-
1%
#230000
b10100 ,
b10011 /
b10011 '
0-
0%
#235000
b10100 !
b10100 6
b10111110 4
1-
1%
#240000
b10101 ,
b10100 /
b10100 '
0-
0%
#245000
b10101 !
b10101 6
b11010010 4
1-
1%
#250000
b10110 ,
b10101 /
b10101 '
0-
0%
#255000
b10110 !
b10110 6
b11100111 4
1-
1%
#260000
b10111 ,
b10110 /
b10110 '
0-
0%
#265000
b10111 !
b10111 6
b11111101 4
1-
1%
#270000
b11000 ,
b10111 /
b10111 '
0-
0%
#275000
b11000 !
b11000 6
b100010100 4
1-
1%
#280000
b11001 ,
b11000 /
b11000 '
0-
0%
#285000
b11001 !
b11001 6
b100101100 4
1-
1%
#290000
b11010 ,
b11001 /
b11001 '
0-
0%
#295000
b11010 !
b11010 6
b101000101 4
1-
1%
#300000
b11011 ,
b11010 /
b11010 '
0-
0%
#305000
b11011 !
b11011 6
b101011111 4
1-
1%
#310000
b11100 ,
b11011 /
b11011 '
0-
0%
#315000
b11100 !
b11100 6
b101111010 4
1-
1%
#320000
b11101 ,
b11100 /
b11100 '
0-
0%
#325000
b11101 !
b11101 6
b110010110 4
1-
1%
#330000
b11110 ,
b11101 /
b11101 '
0-
0%
#335000
b11110 !
b11110 6
b110110011 4
1-
1%
#340000
b11111 ,
b11110 /
b11110 '
0-
0%
#345000
b11111 !
b11111 6
b111010001 4
1-
1%
#350000
b100000 ,
b11111 /
b11111 '
0-
0%
#355000
b100000 !
b100000 6
b111110000 4
1-
1%
#360000
b100001 ,
b100000 /
b100000 '
0-
0%
#365000
b100001 !
b100001 6
b1000010000 4
1-
1%
#370000
b100010 ,
b100001 /
b100001 '
0-
0%
#375000
b100010 !
b100010 6
b1000110001 4
1-
1%
#380000
b100011 ,
b100010 /
b100010 '
0-
0%
#385000
b100011 !
b100011 6
b1001010011 4
1-
1%
#390000
b100100 ,
b100011 /
b100011 '
0-
0%
#395000
b100100 !
b100100 6
b1001110110 4
1-
1%
#400000
b100101 ,
b100100 /
b100100 '
0-
0%
#405000
b100101 !
b100101 6
b1010011010 4
1-
1%
#410000
b100110 ,
b100101 /
b100101 '
0-
0%
#415000
b100110 !
b100110 6
b1010111111 4
1-
1%
#420000
b100111 ,
b100110 /
b100110 '
0-
0%
#425000
b100111 !
b100111 6
b1011100101 4
1-
1%
#430000
b101000 ,
b100111 /
b100111 '
0-
0%
#435000
b101000 !
b101000 6
b1100001100 4
1-
1%
#440000
b101001 ,
b101000 /
b101000 '
0-
0%
#445000
b101001 !
b101001 6
b1100110100 4
1-
1%
#450000
b101010 ,
b101001 /
b101001 '
0-
0%
#455000
b101010 !
b101010 6
b1101011101 4
1-
1%
#460000
b101011 ,
b101010 /
b101010 '
0-
0%
#465000
b101011 !
b101011 6
b1110000111 4
1-
1%
#470000
b101100 ,
b101011 /
b101011 '
0-
0%
#475000
b101100 !
b101100 6
b1110110010 4
1-
1%
#480000
b101101 ,
b101100 /
b101100 '
0-
0%
#485000
b101101 !
b101101 6
b1111011110 4
1-
1%
#490000
b101110 ,
b101101 /
b101101 '
0-
0%
#495000
b101110 !
b101110 6
b10000001011 4
1-
1%
#500000
b101111 ,
b101110 /
b101110 '
0-
0%
#505000
b101111 !
b101111 6
b10000111001 4
1-
1%
#510000
b110000 ,
b101111 /
b101111 '
0-
0%
#515000
b110000 !
b110000 6
b10001101000 4
1-
1%
#520000
b110001 ,
b110000 /
b110000 '
0-
0%
#525000
b110001 !
b110001 6
b10010011000 4
1-
1%
#530000
b110010 ,
b110001 /
b110001 '
0-
0%
#535000
b110010 !
b110010 6
b10011001001 4
1-
1%
#540000
b110011 ,
b110010 /
b110010 '
0-
0%
#545000
b110011 !
b110011 6
b10011111011 4
1-
1%
#550000
b110100 ,
b110011 /
b110011 '
0-
0%
#555000
b110100 !
b110100 6
b10100101110 4
1-
1%
#560000
b110101 ,
b110100 /
b110100 '
0-
0%
#565000
b110101 !
b110101 6
b10101100010 4
1-
1%
#570000
b110110 ,
b110101 /
b110101 '
0-
0%
#575000
b110110 !
b110110 6
b10110010111 4
1-
1%
#580000
b110111 ,
b110110 /
b110110 '
0-
0%
#585000
b110111 !
b110111 6
b10111001101 4
1-
1%
#590000
b111000 ,
b110111 /
b110111 '
0-
0%
#595000
b111000 !
b111000 6
b11000000100 4
1-
1%
#600000
b111001 ,
b111000 /
b111000 '
0-
0%
#605000
b111001 !
b111001 6
b11000111100 4
1-
1%
#610000
b111010 ,
b111001 /
b111001 '
0-
0%
#615000
b111010 !
b111010 6
b11001110101 4
1-
1%
#620000
b111011 ,
b111010 /
b111010 '
0-
0%
#625000
b111011 !
b111011 6
b11010101111 4
1-
1%
#630000
b111100 ,
b111011 /
b111011 '
0-
0%
#635000
b111100 !
b111100 6
b11011101010 4
1-
1%
#640000
b111101 ,
b111100 /
b111100 '
0-
0%
#645000
b111101 !
b111101 6
b11100100110 4
1-
1%
#650000
b111110 ,
b111101 /
b111101 '
0-
0%
#655000
b111110 !
b111110 6
b11101100011 4
1-
1%
#660000
b111111 ,
b111110 /
b111110 '
0-
0%
#665000
b111111 !
b111111 6
b11110100001 4
1-
1%
#670000
b1000000 ,
b111111 /
b111111 '
0-
0%
#675000
b1000000 !
b1000000 6
b11111100000 4
1-
1%
#680000
b1000001 ,
b1000000 /
b1000000 '
0-
0%
#685000
b1000001 !
b1000001 6
b100000100000 4
1-
1%
#690000
b1000010 ,
b1000001 /
b1000001 '
0-
0%
#695000
b1000010 !
b1000010 6
b100001100001 4
1-
1%
#700000
b1000011 ,
b1000010 /
b1000010 '
0-
0%
#705000
b1000011 !
b1000011 6
b100010100011 4
1-
1%
#710000
b1000100 ,
b1000011 /
b1000011 '
0-
0%
#715000
b1000100 !
b1000100 6
b100011100110 4
1-
1%
#720000
b1000101 ,
b1000100 /
b1000100 '
0-
0%
#725000
b1000101 !
b1000101 6
b100100101010 4
1-
1%
#730000
b1000110 ,
b1000101 /
b1000101 '
0-
0%
#735000
b1000110 !
b1000110 6
b100101101111 4
1-
1%
#740000
b1000111 ,
b1000110 /
b1000110 '
0-
0%
#745000
b1000111 !
b1000111 6
b100110110101 4
1-
1%
#750000
b1001000 ,
b1000111 /
b1000111 '
0-
0%
#755000
b1001000 !
b1001000 6
b100111111100 4
1-
1%
#760000
b1001001 ,
b1001000 /
b1001000 '
0-
0%
#765000
b1001001 !
b1001001 6
b101001000100 4
1-
1%
#770000
b1001010 ,
b1001001 /
b1001001 '
0-
0%
#775000
b1001010 !
b1001010 6
b101010001101 4
1-
1%
#780000
b1001011 ,
b1001010 /
b1001010 '
0-
0%
#785000
b1001011 !
b1001011 6
b101011010111 4
1-
1%
#790000
b1001100 ,
b1001011 /
b1001011 '
0-
0%
#795000
b1001100 !
b1001100 6
b101100100010 4
1-
1%
#800000
b1001101 ,
b1001100 /
b1001100 '
0-
0%
#805000
b1001101 !
b1001101 6
b101101101110 4
1-
1%
#810000
b1001110 ,
b1001101 /
b1001101 '
0-
0%
#815000
b1001110 !
b1001110 6
b101110111011 4
1-
1%
#820000
b1001111 ,
b1001110 /
b1001110 '
0-
0%
#825000
b1001111 !
b1001111 6
b110000001001 4
1-
1%
#830000
b1010000 ,
b1001111 /
b1001111 '
0-
0%
#835000
b1010000 !
b1010000 6
b110001011000 4
1-
1%
#840000
b1010001 ,
b1010000 /
b1010000 '
0-
0%
#845000
b1010001 !
b1010001 6
b110010101000 4
1-
1%
#850000
b1010010 ,
b1010001 /
b1010001 '
0-
0%
#855000
b1010010 !
b1010010 6
b110011111001 4
1-
1%
#860000
b1010011 ,
b1010010 /
b1010010 '
0-
0%
#865000
b1010011 !
b1010011 6
b110101001011 4
1-
1%
#870000
b1010100 ,
b1010011 /
b1010011 '
0-
0%
#875000
b1010100 !
b1010100 6
b110110011110 4
1-
1%
#880000
b1010101 ,
b1010100 /
b1010100 '
0-
0%
#885000
b1010101 !
b1010101 6
b110111110010 4
1-
1%
#890000
b1010110 ,
b1010101 /
b1010101 '
0-
0%
#895000
b1010110 !
b1010110 6
b111001000111 4
1-
1%
#900000
b1010111 ,
b1010110 /
b1010110 '
0-
0%
#905000
b1010111 !
b1010111 6
b111010011101 4
1-
1%
#910000
b1011000 ,
b1010111 /
b1010111 '
0-
0%
#915000
b1011000 !
b1011000 6
b111011110100 4
1-
1%
#920000
b1011001 ,
b1011000 /
b1011000 '
0-
0%
#925000
b1011001 !
b1011001 6
b111101001100 4
1-
1%
#930000
b1011010 ,
b1011001 /
b1011001 '
0-
0%
#935000
b1011010 !
b1011010 6
b111110100101 4
1-
1%
#940000
b1011011 ,
b1011010 /
b1011010 '
0-
0%
#945000
b1011011 !
b1011011 6
b111111111111 4
1-
1%
#950000
b1011100 ,
b1011011 /
b1011011 '
0-
0%
#955000
b1011100 !
b1011100 6
b1000001011010 4
1-
1%
#960000
b1011101 ,
b1011100 /
b1011100 '
0-
0%
#965000
b1011101 !
b1011101 6
b1000010110110 4
1-
1%
#970000
b1011110 ,
b1011101 /
b1011101 '
0-
0%
#975000
b1011110 !
b1011110 6
b1000100010011 4
1-
1%
#980000
b1011111 ,
b1011110 /
b1011110 '
0-
0%
#985000
b1011111 !
b1011111 6
b1000101110001 4
1-
1%
#990000
b1100000 ,
b1011111 /
b1011111 '
0-
0%
#995000
b1100000 !
b1100000 6
b1000111010000 4
1-
1%
#1000000
b1100001 ,
b1100000 /
b1100000 '
0-
0%
#1005000
b1100001 !
b1100001 6
b1001000110000 4
1-
1%
#1010000
b1100010 ,
b1100001 /
b1100001 '
0-
0%
#1015000
b1100010 !
b1100010 6
b1001010010001 4
1-
1%
#1020000
b1100011 ,
b1100010 /
b1100010 '
0-
0%
#1025000
b1100011 !
b1100011 6
b1001011110011 4
1-
1%
#1030000
b1100100 ,
b1100011 /
b1100011 '
0-
0%
#1035000
b1100100 !
b1100100 6
b1001101010110 4
1-
1%
#1040000
b1100101 ,
b1100100 /
b1100100 '
0-
0%
#1045000
b1100101 !
b1100101 6
b1001110111010 4
1-
1%
#1050000
b1100110 ,
b1100101 /
b1100101 '
0-
0%
#1055000
b1100110 !
b1100110 6
b1010000011111 4
1-
1%
#1060000
b1100111 ,
b1100110 /
b1100110 '
0-
0%
#1065000
b1100111 !
b1100111 6
b1010010000101 4
1-
1%
#1070000
b1101000 ,
b1100111 /
b1100111 '
0-
0%
#1075000
b1101000 !
b1101000 6
b1010011101100 4
1-
1%
#1080000
b1101001 ,
b1101000 /
b1101000 '
0-
0%
#1085000
b1101001 !
b1101001 6
b1010101010100 4
1-
1%
#1090000
b1101010 ,
b1101001 /
b1101001 '
0-
0%
#1095000
b1101010 !
b1101010 6
b1010110111101 4
1-
1%
#1100000
b1101011 ,
b1101010 /
b1101010 '
0-
0%
#1105000
b1101011 !
b1101011 6
b1011000100111 4
1-
1%
#1110000
b1101100 ,
b1101011 /
b1101011 '
0-
0%
#1115000
b1101100 !
b1101100 6
b1011010010010 4
1-
1%
#1120000
b1101101 ,
b1101100 /
b1101100 '
0-
0%
#1125000
b1101101 !
b1101101 6
b1011011111110 4
1-
1%
#1130000
b1101110 ,
b1101101 /
b1101101 '
0-
0%
#1135000
b1101110 !
b1101110 6
b1011101101011 4
1-
1%
#1140000
b1101111 ,
b1101110 /
b1101110 '
0-
0%
#1145000
b1101111 !
b1101111 6
b1011111011001 4
1-
1%
#1150000
b1110000 ,
b1101111 /
b1101111 '
0-
0%
#1155000
b1110000 !
b1110000 6
b1100001001000 4
1-
1%
#1160000
b1110001 ,
b1110000 /
b1110000 '
0-
0%
#1165000
b1110001 !
b1110001 6
b1100010111000 4
1-
1%
#1170000
b1110010 ,
b1110001 /
b1110001 '
0-
0%
#1175000
b1110010 !
b1110010 6
b1100100101001 4
1-
1%
#1180000
b1110011 ,
b1110010 /
b1110010 '
0-
0%
#1185000
b1110011 !
b1110011 6
b1100110011011 4
1-
1%
#1190000
b1110100 ,
b1110011 /
b1110011 '
0-
0%
#1195000
b1110100 !
b1110100 6
b1101000001110 4
1-
1%
#1200000
b1110101 ,
b1110100 /
b1110100 '
0-
0%
#1205000
b1110101 !
b1110101 6
b1101010000010 4
1-
1%
#1210000
b1110110 ,
b1110101 /
b1110101 '
0-
0%
#1215000
b1110110 !
b1110110 6
b1101011110111 4
1-
1%
#1220000
b1110111 ,
b1110110 /
b1110110 '
0-
0%
#1225000
b1110111 !
b1110111 6
b1101101101101 4
1-
1%
#1230000
b1111000 ,
b1110111 /
b1110111 '
0-
0%
#1235000
b1111000 !
b1111000 6
b1101111100100 4
1-
1%
#1240000
b1111001 ,
b1111000 /
b1111000 '
0-
0%
#1245000
b1111001 !
b1111001 6
b1110001011100 4
1-
1%
#1250000
b1111010 ,
b1111001 /
b1111001 '
0-
0%
#1255000
b1111010 !
b1111010 6
b1110011010101 4
1-
1%
#1260000
b1111011 ,
b1111010 /
b1111010 '
0-
0%
#1265000
b1111011 !
b1111011 6
b1110101001111 4
1-
1%
#1270000
b1111100 ,
b1111011 /
b1111011 '
0-
0%
#1275000
b1111100 !
b1111100 6
b1110111001010 4
1-
1%
#1280000
b1111101 ,
b1111100 /
b1111100 '
0-
0%
#1285000
b1111101 !
b1111101 6
b1111001000110 4
1-
1%
#1290000
b1111110 ,
b1111101 /
b1111101 '
0-
0%
#1295000
b1111110 !
b1111110 6
b1111011000011 4
1-
1%
#1300000
b1111111 ,
b1111110 /
b1111110 '
0-
0%
#1305000
b1111111 !
b1111111 6
b1111101000001 4
1-
1%
#1310000
b10000000 ,
b1111111 /
b1111111 '
0-
0%
#1315000
b10000000 !
b10000000 6
b1111111000000 4
1-
1%
#1320000
b10000001 ,
b10000000 /
b10000000 '
0-
0%
#1325000
b10000001 !
b10000001 6
b10000001000000 4
1-
1%
#1330000
b10000010 ,
b10000001 /
b10000001 '
0-
0%
#1335000
b10000010 !
b10000010 6
b10000011000001 4
1-
1%
#1340000
b10000011 ,
b10000010 /
b10000010 '
0-
0%
#1345000
b10000011 !
b10000011 6
b10000101000011 4
1-
1%
#1350000
b10000100 ,
b10000011 /
b10000011 '
0-
0%
#1355000
b10000100 !
b10000100 6
b10000111000110 4
1-
1%
#1360000
b10000101 ,
b10000100 /
b10000100 '
0-
0%
#1365000
b10000101 !
b10000101 6
b10001001001010 4
1-
1%
#1370000
b10000110 ,
b10000101 /
b10000101 '
0-
0%
#1375000
b10000110 !
b10000110 6
b10001011001111 4
1-
1%
#1380000
b10000111 ,
b10000110 /
b10000110 '
0-
0%
#1385000
b10000111 !
b10000111 6
b10001101010101 4
1-
1%
#1390000
b10001000 ,
b10000111 /
b10000111 '
0-
0%
#1395000
b10001000 !
b10001000 6
b10001111011100 4
1-
1%
#1400000
b10001001 ,
b10001000 /
b10001000 '
0-
0%
#1405000
b10001001 !
b10001001 6
b10010001100100 4
1-
1%
#1410000
b10001010 ,
b10001001 /
b10001001 '
0-
0%
#1415000
b10001010 !
b10001010 6
b10010011101101 4
1-
1%
#1420000
b10001011 ,
b10001010 /
b10001010 '
0-
0%
#1425000
b10001011 !
b10001011 6
b10010101110111 4
1-
1%
#1430000
b10001100 ,
b10001011 /
b10001011 '
0-
0%
#1435000
b10001100 !
b10001100 6
b10011000000010 4
1-
1%
#1440000
b10001101 ,
b10001100 /
b10001100 '
0-
0%
#1445000
b10001101 !
b10001101 6
b10011010001110 4
1-
1%
#1450000
b10001110 ,
b10001101 /
b10001101 '
0-
0%
#1455000
b10001110 !
b10001110 6
b10011100011011 4
1-
1%
#1460000
b10001111 ,
b10001110 /
b10001110 '
0-
0%
#1465000
b10001111 !
b10001111 6
b10011110101001 4
1-
1%
#1470000
b10010000 ,
b10001111 /
b10001111 '
0-
0%
#1475000
b10010000 !
b10010000 6
b10100000111000 4
1-
1%
#1480000
b10010001 ,
b10010000 /
b10010000 '
0-
0%
#1485000
b10010001 !
b10010001 6
b10100011001000 4
1-
1%
#1490000
b10010010 ,
b10010001 /
b10010001 '
0-
0%
#1495000
b10010010 !
b10010010 6
b10100101011001 4
1-
1%
#1500000
b10010011 ,
b10010010 /
b10010010 '
0-
0%
#1505000
b10010011 !
b10010011 6
b10100111101011 4
1-
1%
#1510000
b10010100 ,
b10010011 /
b10010011 '
0-
0%
#1515000
b10010100 !
b10010100 6
b10101001111110 4
1-
1%
#1520000
b10010101 ,
b10010100 /
b10010100 '
0-
0%
#1525000
b10010101 !
b10010101 6
b10101100010010 4
1-
1%
#1530000
b10010110 ,
b10010101 /
b10010101 '
0-
0%
#1535000
b10010110 !
b10010110 6
b10101110100111 4
1-
1%
#1540000
b10010111 ,
b10010110 /
b10010110 '
0-
0%
#1545000
b10010111 !
b10010111 6
b10110000111101 4
1-
1%
#1550000
b10011000 ,
b10010111 /
b10010111 '
0-
0%
#1555000
b10011000 !
b10011000 6
b10110011010100 4
1-
1%
#1560000
b10011001 ,
b10011000 /
b10011000 '
0-
0%
#1565000
b10011001 !
b10011001 6
b10110101101100 4
1-
1%
#1570000
b10011010 ,
b10011001 /
b10011001 '
0-
0%
#1575000
b10011010 !
b10011010 6
b10111000000101 4
1-
1%
#1580000
b10011011 ,
b10011010 /
b10011010 '
0-
0%
#1585000
b10011011 !
b10011011 6
b10111010011111 4
1-
1%
#1590000
b10011100 ,
b10011011 /
b10011011 '
0-
0%
#1595000
b10011100 !
b10011100 6
b10111100111010 4
1-
1%
#1600000
b10011101 ,
b10011100 /
b10011100 '
0-
0%
#1605000
b10011101 !
b10011101 6
b10111111010110 4
1-
1%
#1610000
b10011110 ,
b10011101 /
b10011101 '
0-
0%
#1615000
b10011110 !
b10011110 6
b11000001110011 4
1-
1%
#1620000
b10011111 ,
b10011110 /
b10011110 '
0-
0%
#1625000
b10011111 !
b10011111 6
b11000100010001 4
1-
1%
#1630000
b10100000 ,
b10011111 /
b10011111 '
0-
0%
#1635000
b10100000 !
b10100000 6
b11000110110000 4
1-
1%
#1640000
b10100001 ,
b10100000 /
b10100000 '
0-
0%
#1645000
b10100001 !
b10100001 6
b11001001010000 4
1-
1%
#1650000
b10100010 ,
b10100001 /
b10100001 '
0-
0%
#1655000
b10100010 !
b10100010 6
b11001011110001 4
1-
1%
#1660000
b10100011 ,
b10100010 /
b10100010 '
0-
0%
#1665000
b10100011 !
b10100011 6
b11001110010011 4
1-
1%
#1670000
b10100100 ,
b10100011 /
b10100011 '
0-
0%
#1675000
b10100100 !
b10100100 6
b11010000110110 4
1-
1%
#1680000
b10100101 ,
b10100100 /
b10100100 '
0-
0%
#1685000
b10100101 !
b10100101 6
b11010011011010 4
1-
1%
#1690000
b10100110 ,
b10100101 /
b10100101 '
0-
0%
#1695000
b10100110 !
b10100110 6
b11010101111111 4
1-
1%
#1700000
b10100111 ,
b10100110 /
b10100110 '
0-
0%
#1705000
b10100111 !
b10100111 6
b11011000100101 4
1-
1%
#1710000
b10101000 ,
b10100111 /
b10100111 '
0-
0%
#1715000
b10101000 !
b10101000 6
b11011011001100 4
1-
1%
#1720000
b10101001 ,
b10101000 /
b10101000 '
0-
0%
#1725000
b10101001 !
b10101001 6
b11011101110100 4
1-
1%
#1730000
b10101010 ,
b10101001 /
b10101001 '
0-
0%
#1735000
b10101010 !
b10101010 6
b11100000011101 4
1-
1%
#1740000
b10101011 ,
b10101010 /
b10101010 '
0-
0%
#1745000
b10101011 !
b10101011 6
b11100011000111 4
1-
1%
#1750000
b10101100 ,
b10101011 /
b10101011 '
0-
0%
#1755000
b10101100 !
b10101100 6
b11100101110010 4
1-
1%
#1760000
b10101101 ,
b10101100 /
b10101100 '
0-
0%
#1765000
b10101101 !
b10101101 6
b11101000011110 4
1-
1%
#1770000
b10101110 ,
b10101101 /
b10101101 '
0-
0%
#1775000
b10101110 !
b10101110 6
b11101011001011 4
1-
1%
#1780000
b10101111 ,
b10101110 /
b10101110 '
0-
0%
#1785000
b10101111 !
b10101111 6
b11101101111001 4
1-
1%
#1790000
b10110000 ,
b10101111 /
b10101111 '
0-
0%
#1795000
b10110000 !
b10110000 6
b11110000101000 4
1-
1%
#1800000
b10110001 ,
b10110000 /
b10110000 '
0-
0%
#1805000
b10110001 !
b10110001 6
b11110011011000 4
1-
1%
#1810000
b10110010 ,
b10110001 /
b10110001 '
0-
0%
#1815000
b10110010 !
b10110010 6
b11110110001001 4
1-
1%
#1820000
b10110011 ,
b10110010 /
b10110010 '
0-
0%
#1825000
b10110011 !
b10110011 6
b11111000111011 4
1-
1%
#1830000
b10110100 ,
b10110011 /
b10110011 '
0-
0%
#1835000
b10110100 !
b10110100 6
b11111011101110 4
1-
1%
#1840000
b10110101 ,
b10110100 /
b10110100 '
0-
0%
#1845000
b10110101 !
b10110101 6
b11111110100010 4
1-
1%
#1850000
b10110110 ,
b10110101 /
b10110101 '
0-
0%
#1855000
b10110110 !
b10110110 6
b100000001010111 4
1-
1%
#1860000
b10110111 ,
b10110110 /
b10110110 '
0-
0%
#1865000
b10110111 !
b10110111 6
b100000100001101 4
1-
1%
#1870000
b10111000 ,
b10110111 /
b10110111 '
0-
0%
#1875000
b10111000 !
b10111000 6
b100000111000100 4
1-
1%
#1880000
b10111001 ,
b10111000 /
b10111000 '
0-
0%
#1885000
b10111001 !
b10111001 6
b100001001111100 4
1-
1%
#1890000
b10111010 ,
b10111001 /
b10111001 '
0-
0%
#1895000
b10111010 !
b10111010 6
b100001100110101 4
1-
1%
#1900000
b10111011 ,
b10111010 /
b10111010 '
0-
0%
#1905000
b10111011 !
b10111011 6
b100001111101111 4
1-
1%
#1910000
b10111100 ,
b10111011 /
b10111011 '
0-
0%
#1915000
b10111100 !
b10111100 6
b100010010101010 4
1-
1%
#1920000
b10111101 ,
b10111100 /
b10111100 '
0-
0%
#1925000
b10111101 !
b10111101 6
b100010101100110 4
1-
1%
#1930000
b10111110 ,
b10111101 /
b10111101 '
0-
0%
#1935000
b10111110 !
b10111110 6
b100011000100011 4
1-
1%
#1940000
b10111111 ,
b10111110 /
b10111110 '
0-
0%
#1945000
b10111111 !
b10111111 6
b100011011100001 4
1-
1%
#1950000
b11000000 ,
b10111111 /
b10111111 '
0-
0%
#1955000
b11000000 !
b11000000 6
b100011110100000 4
1-
1%
#1960000
b11000001 ,
b11000000 /
b11000000 '
0-
0%
#1965000
b11000001 !
b11000001 6
b100100001100000 4
1-
1%
#1970000
b11000010 ,
b11000001 /
b11000001 '
0-
0%
#1975000
b11000010 !
b11000010 6
b100100100100001 4
1-
1%
#1980000
b11000011 ,
b11000010 /
b11000010 '
0-
0%
#1985000
b11000011 !
b11000011 6
b100100111100011 4
1-
1%
#1990000
b11000100 ,
b11000011 /
b11000011 '
0-
0%
#1995000
b11000100 !
b11000100 6
b100101010100110 4
1-
1%
#2000000
b11000101 ,
b11000100 /
b11000100 '
0-
0%
#2005000
b11000101 !
b11000101 6
b100101101101010 4
1-
1%
#2010000
b11000110 ,
b11000101 /
b11000101 '
0-
0%
#2015000
b11000110 !
b11000110 6
b100110000101111 4
1-
1%
#2020000
b11000111 ,
b11000110 /
b11000110 '
0-
0%
#2025000
b11000111 !
b11000111 6
b100110011110101 4
1-
1%
#2030000
b11001000 ,
b11000111 /
b11000111 '
0-
0%
#2035000
b11001000 !
b11001000 6
b100110110111100 4
1-
1%
#2040000
b11001001 ,
b11001000 /
b11001000 '
0-
0%
#2045000
b11001001 !
b11001001 6
b100111010000100 4
1-
1%
#2050000
b11001010 ,
b11001001 /
b11001001 '
0-
0%
